my_test_distributions/Binomialdistribution.py
my_test_distributions/Gaussiandistribution.py
my_test_distributions/Generaldistribution.py
my_test_distributions/__init__.py
my_test_distributions-0.1.dist-info/DESCRIPTION.rst
my_test_distributions-0.1.dist-info/METADATA
my_test_distributions-0.1.dist-info/RECORD
my_test_distributions-0.1.dist-info/WHEEL
my_test_distributions-0.1.dist-info/metadata.json
my_test_distributions-0.1.dist-info/top_level.txt
